ferret/__init__.py
ferret/benchmark.py
ferret/model_utils.py
ferret/datasets/__init__.py
ferret/datasets/datamanagers.py
ferret/datasets/datamanagers_thermostat.py
ferret/datasets/utils_sst_rationale_generation.py
ferret/evaluators/__init__.py
ferret/evaluators/class_measures.py
ferret/evaluators/evaluation.py
ferret/evaluators/faithfulness_measures.py
ferret/evaluators/plausibility_measures.py
ferret/evaluators/utils_from_soft_to_discrete.py
ferret/explainers/__init__.py
ferret/explainers/dummy.py
ferret/explainers/explanation.py
ferret/explainers/gradient.py
ferret/explainers/lime.py
ferret/explainers/shap.py
ferret/explainers/utils.py
ferret/explainers/soc/__init__.py
ferret/explainers/soc/agglomeration.py
ferret/explainers/soc/common.py
ferret/explainers/soc/config.py
ferret/explainers/soc/layers.py
ferret/explainers/soc/lm.py
ferret/explainers/soc/processor.py
ferret/explainers/soc/soc_algo.py
ferret/explainers/soc/soc_api.py
ferret/explainers/soc/train_lm.py
ferret_xai-0.4.1.dist-info/AUTHORS.rst
ferret_xai-0.4.1.dist-info/LICENSE
ferret_xai-0.4.1.dist-info/METADATA
ferret_xai-0.4.1.dist-info/WHEEL
ferret_xai-0.4.1.dist-info/top_level.txt
ferret_xai-0.4.1.dist-info/RECORD
