Metadata-Version: 2.1
Name: ferret-xai
Version: 0.4.1
Summary: A python package for benchmarking interpretability approaches.
Home-page: https://github.com/g8a9/ferret
Author: Giuseppe Attanasio
Author-email: giuseppeattanasio6@gmail.com
License: MIT license
Keywords: ferret
Classifier: Development Status :: 2 - Pre-Alpha
Classifier: Intended Audience :: Developers
Classifier: License :: OSI Approved :: MIT License
Classifier: Natural Language :: English
Classifier: Programming Language :: Python :: 3
Classifier: Programming Language :: Python :: 3.6
Requires-Python: >=3.7
License-File: LICENSE
License-File: AUTHORS.rst
Requires-Dist: transformers
Requires-Dist: datasets
Requires-Dist: sentencepiece
Requires-Dist: captum
Requires-Dist: shap
Requires-Dist: seaborn
Requires-Dist: matplotlib
Requires-Dist: numpy
Requires-Dist: pandas
Requires-Dist: tqdm
Requires-Dist: scikit-image
Requires-Dist: opencv-python
Requires-Dist: lime
Requires-Dist: joblib
Requires-Dist: pytreebank
Requires-Dist: thermostat-datasets
